PyPowerStore/__init__.py
PyPowerStore/client.py
PyPowerStore/configuration.py
PyPowerStore/powerstore_conn.py
PyPowerStore/protection.py
PyPowerStore/provisioning.py
PyPowerStore/objects/__init__.py
PyPowerStore/objects/file_dns.py
PyPowerStore/objects/file_interface.py
PyPowerStore/objects/file_nis.py
PyPowerStore/objects/nfs_server.py
PyPowerStore/objects/smb_server.py
PyPowerStore/objects/snmp_server.py
PyPowerStore/utils/__init__.py
PyPowerStore/utils/constants.py
PyPowerStore/utils/exception.py
PyPowerStore/utils/helpers.py
pypowerstore-3.4.1.0.dist-info/licenses/LICENSE
pypowerstore-3.4.1.0.dist-info/METADATA
pypowerstore-3.4.1.0.dist-info/WHEEL
pypowerstore-3.4.1.0.dist-info/top_level.txt
pypowerstore-3.4.1.0.dist-info/RECORD
