Metadata-Version: 2.4
Name: PyPowerStore
Version: 3.4.1.0
Summary: Python Library for Dell PowerStore
Home-page: https://github.com/dell/python-powerstore
Author: Ansible Team at Dell
Author-email: ansible.team@dell.com
Classifier: License :: OSI Approved :: Apache Software License
License-File: LICENSE
Requires-Dist: urllib3>=1.26.7
Requires-Dist: requests>=2.23.0
Dynamic: author
Dynamic: author-email
Dynamic: classifier
Dynamic: home-page
Dynamic: license-file
Dynamic: requires-dist
Dynamic: summary
